pyGUS/__init__.py
pyGUS/__main__.py
pyGUS/cfm.py
pyGUS/core.py
pyGUS/deprecated.py
pyGUS/global_vars.py
pyGUS/ui.py
pyGUS/utils.py
pyGUS/data/Manual.pdf
pyGUS/data/Mode1-negative-reference.jpg
pyGUS/data/Mode1-positive-reference.jpg
pyGUS/data/Mode1-sample-1.jpg
pyGUS/data/Mode1-sample-2.jpg
pyGUS/data/Mode2-Positive-reference.jpg
pyGUS/data/Mode2-negative-reference.jpg
pyGUS/data/Mode2-sample.jpg
pyGUS/data/Mode3-negative-reference.jpg
pyGUS/data/Mode3-positive-reference.jpg
pyGUS/data/Mode3-sample.jpg
pyGUS/data/Mode4.jpg
pyGUS/data/color_checker.jpg
pygus_bio-1.10.dist-info/METADATA
pygus_bio-1.10.dist-info/WHEEL
pygus_bio-1.10.dist-info/licenses/LICENSE
pygus_bio-1.10.dist-info/RECORD
