Metadata-Version: 2.3
Name: pyGUS_bio
Version: 1.10
Summary: Quantify GUS Stain Images
Project-URL: Homepage, https://github.com/wpwupingwp/pyGUS
Author-email: Ping Wu <wpwupingwp@outlook.com>
License: GNU AGPL v3
Classifier: Development Status :: 5 - Production/Stable
Classifier: Intended Audience :: Science/Research
Classifier: License :: OSI Approved :: GNU Affero General Public License v3
Classifier: Operating System :: OS Independent
Classifier: Programming Language :: Python :: 3
Classifier: Topic :: Scientific/Engineering :: Bio-Informatics
Requires-Python: >=3.12
Requires-Dist: coloredlogs>=15.0.1
Requires-Dist: colour-science>=0.4.4
Requires-Dist: matplotlib>=3.5.2
Requires-Dist: numpy<2
Requires-Dist: opencv-contrib-python>=4.8.1.78
Requires-Dist: scipy>=1.11.1
Requires-Dist: tqdm==4.66.3
